webunity/__init__.py
webunity/formatter.py
webunity/loader.py
webunity/middleware.py
webunity/urls.py
webunity/views.py
webunity/account/__init__.py
webunity/account/admin.py
webunity/account/apps.py
webunity/account/models.py
webunity/account/utils.py
webunity/account/management/__init__.py
webunity/account/management/commands/__init__.py
webunity/account/management/commands/account.py
webunity/account/migrations/0001_initial.py
webunity/account/migrations/0002_auto_20200702_1608.py
webunity/account/migrations/0003_auto_20200702_1747.py
webunity/account/migrations/0004_auto_20200702_1758.py
webunity/account/migrations/0005_auto_20200702_1830.py
webunity/account/migrations/0006_auto_20200702_2018.py
webunity/account/migrations/__init__.py
webunity/bakery/__init__.py
webunity/bakery/abstract.py
webunity/bakery/apps.py
webunity/bakery/exceptions.py
webunity/bakery/tasks.py
webunity/bakery/wagtail_hooks.py
webunity/bakery/management/__init__.py
webunity/bakery/management/commands/__init__.py
webunity/bakery/management/commands/build.py
webunity/bakery/migrations/__init__.py
webunity/bakery/views/__init__.py
webunity/bakery/views/base.py
webunity/bakery/views/detail.py
webunity/bakery/views/wagtail.py
webunity/cms/__init__.py
webunity/cms/apps.py
webunity/cms/constants.py
webunity/cms/models.py
webunity/cms/wagtail_hooks.py
webunity/cms/blocks/__init__.py
webunity/cms/blocks/choice.py
webunity/cms/blocks/common.py
webunity/cms/blocks/mocker.py
webunity/cms/blocks/schemas.py
webunity/cms/blocks/actions/__init__.py
webunity/cms/blocks/actions/email.py
webunity/cms/blocks/actions/manager.py
webunity/cms/blocks/entries/__init__.py
webunity/cms/blocks/entries/accordion.py
webunity/cms/blocks/entries/articles.py
webunity/cms/blocks/entries/buttons.py
webunity/cms/blocks/entries/calendly.py
webunity/cms/blocks/entries/cards.py
webunity/cms/blocks/entries/component_text.py
webunity/cms/blocks/entries/embed.py
webunity/cms/blocks/entries/form.py
webunity-0.0.3.dist-info/LICENSE
webunity-0.0.3.dist-info/METADATA
webunity-0.0.3.dist-info/WHEEL
webunity-0.0.3.dist-info/top_level.txt
webunity-0.0.3.dist-info/RECORD
