Metadata-Version: 2.1
Name: webunity
Version: 0.0.3
Summary: Utils for web
Home-page: https://github.com/Aleksi44/webunity
Author: Alexis Le Baron
Author-email: alexis@stationspatiale.com
License: BSD
Keywords: web
Platform: linux
